zycelium/__init__.py
zycelium/agent.py
zycelium/logging.py
zycelium/transport.py
zycelium-2025.4.0.dist-info/LICENSE
zycelium-2025.4.0.dist-info/METADATA
zycelium-2025.4.0.dist-info/WHEEL
zycelium-2025.4.0.dist-info/entry_points.txt
zycelium-2025.4.0.dist-info/RECORD
